vega/__init__.py
vega/auth.py
vega/client.py
vega/grpc/__init__.py
vega/grpc/client.py
vega/pow.py
vega/proto/__init__.py
vega/proto/blockexplorer/api/v1/blockexplorer_pb2.py
vega/proto/blockexplorer/api/v1/blockexplorer_pb2_grpc.py
vega/proto/data_node/__init__.py
vega/proto/data_node/api/__init__.py
vega/proto/data_node/api/v2/__init__.py
vega/proto/data_node/api/v2/trading_data_pb2.py
vega/proto/data_node/api/v2/trading_data_pb2_grpc.py
vega/proto/vega/__init__.py
vega/proto/vega/api/__init__.py
vega/proto/vega/api/v1/__init__.py
vega/proto/vega/api/v1/core_pb2.py
vega/proto/vega/api/v1/core_pb2_grpc.py
vega/proto/vega/api/v1/corestate_pb2.py
vega/proto/vega/api/v1/corestate_pb2_grpc.py
vega/proto/vega/assets_pb2.py
vega/proto/vega/assets_pb2_grpc.py
vega/proto/vega/chain_events_pb2.py
vega/proto/vega/chain_events_pb2_grpc.py
vega/proto/vega/checkpoint/__init__.py
vega/proto/vega/checkpoint/v1/__init__.py
vega/proto/vega/checkpoint/v1/checkpoint_pb2.py
vega/proto/vega/checkpoint/v1/checkpoint_pb2_grpc.py
vega/proto/vega/commands/__init__.py
vega/proto/vega/commands/v1/__init__.py
vega/proto/vega/commands/v1/commands_pb2.py
vega/proto/vega/commands/v1/commands_pb2_grpc.py
vega/proto/vega/commands/v1/data_pb2.py
vega/proto/vega/commands/v1/data_pb2_grpc.py
vega/proto/vega/commands/v1/signature_pb2.py
vega/proto/vega/commands/v1/signature_pb2_grpc.py
vega/proto/vega/commands/v1/transaction_pb2.py
vega/proto/vega/commands/v1/transaction_pb2_grpc.py
vega/proto/vega/commands/v1/validator_commands_pb2.py
vega/proto/vega/commands/v1/validator_commands_pb2_grpc.py
vega/proto/vega/data/__init__.py
vega/proto/vega/data/v1/__init__.py
vega/proto/vega/data/v1/data_pb2.py
vega/proto/vega/data/v1/data_pb2_grpc.py
vega/proto/vega/data/v1/spec_pb2.py
vega/proto/vega/data/v1/spec_pb2_grpc.py
vega/proto/vega/data_source_pb2.py
vega/proto/vega/data_source_pb2_grpc.py
vega/proto/vega/events/__init__.py
vega/proto/vega/events/v1/__init__.py
vega/proto/vega/events/v1/events_pb2.py
vega_python_sdk-0.1.3.dist-info/LICENSE
vega_python_sdk-0.1.3.dist-info/METADATA
vega_python_sdk-0.1.3.dist-info/WHEEL
vega_python_sdk-0.1.3.dist-info/RECORD
